odoo10_addon_test_onchange_helper-10.0.2.1.0-nspkg.pth
odoo/addons/test_onchange_helper/README.rst
odoo/addons/test_onchange_helper/__init__.py
odoo/addons/test_onchange_helper/__manifest__.py
odoo/addons/test_onchange_helper/demo/test_onchange_helper_discussion.xml
odoo/addons/test_onchange_helper/demo/test_onchange_helper_message.xml
odoo/addons/test_onchange_helper/i18n/test_onchange_helper.pot
odoo/addons/test_onchange_helper/models/__init__.py
odoo/addons/test_onchange_helper/models/test_onchange_helper_category.py
odoo/addons/test_onchange_helper/models/test_onchange_helper_discussion.py
odoo/addons/test_onchange_helper/models/test_onchange_helper_emailmessage.py
odoo/addons/test_onchange_helper/models/test_onchange_helper_message.py
odoo/addons/test_onchange_helper/models/test_onchange_helper_multi.py
odoo/addons/test_onchange_helper/models/test_onchange_helper_multi_line.py
odoo/addons/test_onchange_helper/readme/CONTRIBUTORS.rst
odoo/addons/test_onchange_helper/readme/DESCRIPTION.rst
odoo/addons/test_onchange_helper/security/test_onchange_helper_category.xml
odoo/addons/test_onchange_helper/security/test_onchange_helper_discussion.xml
odoo/addons/test_onchange_helper/security/test_onchange_helper_emailmessage.xml
odoo/addons/test_onchange_helper/security/test_onchange_helper_message.xml
odoo/addons/test_onchange_helper/security/test_onchange_helper_multi.xml
odoo/addons/test_onchange_helper/security/test_onchange_helper_multi_line.xml
odoo/addons/test_onchange_helper/static/description/icon.png
odoo/addons/test_onchange_helper/static/description/index.html
odoo/addons/test_onchange_helper/tests/__init__.py
odoo/addons/test_onchange_helper/tests/test_onchange_helper.py
odoo10_addon_test_onchange_helper-10.0.2.1.0.dist-info/METADATA
odoo10_addon_test_onchange_helper-10.0.2.1.0.dist-info/WHEEL
odoo10_addon_test_onchange_helper-10.0.2.1.0.dist-info/namespace_packages.txt
odoo10_addon_test_onchange_helper-10.0.2.1.0.dist-info/top_level.txt
odoo10_addon_test_onchange_helper-10.0.2.1.0.dist-info/RECORD
