Metadata-Version: 2.1
Name: odoo10-addon-test-onchange-helper
Version: 10.0.2.1.0
Summary: Test addon for the onchange_helper addon
Home-page: https://acsone.eu/
Author: ACSONE SA/NV,Odoo Community Association (OCA)
Author-email: support@odoo-community.org
License: AGPL-3
Platform: UNKNOWN
Classifier: Programming Language :: Python
Classifier: Framework :: Odoo
Classifier: License :: OSI Approved :: GNU Affero General Public License v3
Requires-Python: ~=2.7
Requires-Dist: odoo10-addon-onchange-helper
Requires-Dist: odoo (<10.1dev,>=10.0)
